data3_network/__init__.py
data3_network/data_access.py
data3_network-0.0.6.dist-info/METADATA
data3_network-0.0.6.dist-info/WHEEL
data3_network-0.0.6.dist-info/top_level.txt
data3_network-0.0.6.dist-info/RECORD
